nimbus_bci/__init__.py
nimbus_bci/nimbus_math.py
nimbus_bci/nimbus_io.py
nimbus_bci/py.typed
nimbus_bci/metrics/diagnostics.py
nimbus_bci/metrics/__init__.py
nimbus_bci/metrics/performance.py
nimbus_bci/metrics/quality.py
nimbus_bci/metrics/calibration.py
nimbus_bci/compat/__init__.py
nimbus_bci/compat/sklearn_compat.py
nimbus_bci/compat/mne_compat.py
nimbus_bci/utils/__init__.py
nimbus_bci/utils/feature_aggregation.py
nimbus_bci/utils/state_diagnostics.py
nimbus_bci/utils/normalization.py
nimbus_bci/utils/preprocessing_diagnostics.py
nimbus_bci/models/__init__.py
nimbus_bci/models/base.py
nimbus_bci/models/nimbus_lda/classifier.py
nimbus_bci/models/nimbus_lda/__init__.py
nimbus_bci/models/nimbus_lda/inference.cpython-311-darwin.so
nimbus_bci/models/nimbus_lda/inference.py
nimbus_bci/models/nimbus_lda/learning.py
nimbus_bci/models/nimbus_lda/learning.cpython-311-darwin.so
nimbus_bci/models/nimbus_qda/classifier.py
nimbus_bci/models/nimbus_qda/__init__.py
nimbus_bci/models/nimbus_qda/inference.cpython-311-darwin.so
nimbus_bci/models/nimbus_qda/inference.py
nimbus_bci/models/nimbus_qda/learning.py
nimbus_bci/models/nimbus_qda/learning.cpython-311-darwin.so
nimbus_bci/models/nimbus_sts/classifier.py
nimbus_bci/models/nimbus_sts/__init__.py
nimbus_bci/models/nimbus_sts/inference.cpython-311-darwin.so
nimbus_bci/models/nimbus_sts/inference.py
nimbus_bci/models/nimbus_sts/learning.py
nimbus_bci/models/nimbus_sts/learning.cpython-311-darwin.so
nimbus_bci/models/nimbus_softmax/classifier.py
nimbus_bci/models/nimbus_softmax/__init__.py
nimbus_bci/models/nimbus_softmax/inference.cpython-311-darwin.so
nimbus_bci/models/nimbus_softmax/inference.py
nimbus_bci/models/nimbus_softmax/learning.py
nimbus_bci/models/nimbus_softmax/learning.cpython-311-darwin.so
nimbus_bci/inference/aggregation.py
nimbus_bci/inference/dispatch.py
nimbus_bci/inference/batch.py
nimbus_bci/inference/__init__.py
nimbus_bci/inference/streaming.py
nimbus_bci-0.3.0.dist-info/RECORD
nimbus_bci-0.3.0.dist-info/WHEEL
nimbus_bci-0.3.0.dist-info/top_level.txt
nimbus_bci-0.3.0.dist-info/METADATA
nimbus_bci-0.3.0.dist-info/licenses/LICENSE.txt
