Metadata-Version: 2.4
Name: nimbus-bci
Version: 0.3.0
Summary: Nimbus BCI: Bayesian classifiers for brain-computer interfaces
Author-email: "Nimbus BCI Inc." <hello@nimbusbci.com>
License: NIMBUS PYSDK SOFTWARE LICENSE AGREEMENT
Project-URL: Homepage, https://nimbusbci.com
Project-URL: Documentation, https://docs.nimbusbci.com
Project-URL: Repository, https://github.com/nimbusbci/nimbuspysdk
Project-URL: Issues, https://github.com/nimbusbci/nimbuspysdk/issues
Keywords: bci,eeg,machine-learning,bayesian,classification,sklearn
Classifier: Development Status :: 4 - Beta
Classifier: Intended Audience :: Science/Research
Classifier: License :: Other/Proprietary License
Classifier: Programming Language :: Python :: 3
Classifier: Programming Language :: Python :: 3.10
Classifier: Programming Language :: Python :: 3.11
Classifier: Programming Language :: Python :: 3.12
Classifier: Topic :: Scientific/Engineering :: Artificial Intelligence
Requires-Python: >=3.10
License-File: LICENSE.txt
Requires-Dist: numpy>=1.26
Requires-Dist: scikit-learn>=1.4
Provides-Extra: dev
Requires-Dist: pytest>=8.0; extra == "dev"
Requires-Dist: python-dateutil>=2.9.0; extra == "dev"
Requires-Dist: Cython>=3.0; extra == "dev"
Requires-Dist: build; extra == "dev"
Requires-Dist: twine; extra == "dev"
Provides-Extra: viz
Requires-Dist: matplotlib>=3.8; extra == "viz"
Provides-Extra: mne
Requires-Dist: mne>=1.6; extra == "mne"
Provides-Extra: softmax
Requires-Dist: jax>=0.4.25; extra == "softmax"
Provides-Extra: all
Requires-Dist: matplotlib>=3.8; extra == "all"
Requires-Dist: mne>=1.6; extra == "all"
Requires-Dist: scipy>=1.12; extra == "all"
Requires-Dist: jax>=0.4.25; extra == "all"
Dynamic: license-file
